2021/src/average.vhd
library ieee;
use ieee.std_logic_1164.all;
use ieee.numeric_std.all;

entity average is
generic (
    g_data_size : integer:=10
);
    port (
        clk   : in std_logic;
        reset : in std_logic;
        a_in : in std_logic_vector(g_data_size-1 downto 0);
        b_in : in std_logic_vector(g_data_size-1 downto 0);
        avg_out : out std_logic_vector(g_data_size-1 downto 0)
    );
end entity;

architecture rtl of average is
    
  signal s_a_in : std_logic_vector(g_data_size-1 downto 0):=(others => '0') ;
  signal s_b_in : std_logic_vector(g_data_size-1 downto 0):=(others => '0') ;
    signal s_avg_out : std_logic_vector (g_data_size downto 0):=(others => '0') ;

begin
process (clk)
begin
    if rising_edge(clk) then
        if reset = '1' then
            s_avg_out<=(others => '0'); 
        else
            s_a_in<=a_in;
            s_b_in<=b_in;
            s_avg_out<= std_logic_vector(resize(unsigned(s_a_in),g_data_size+1)+resize(unsigned(s_b_in),g_data_size+1));
            avg_out<=std_logic_vector(resize(shift_right(unsigned(s_avg_out),1),g_data_size));
        end if;
    end if;
end process;

end architecture;

2021/tb/func.vcd
$date
  Mon Jul  5 01:53:45 2021
$end
$version
  GHDL v0
$end
$timescale
  1 fs
$end
$scope module standard $end
$upscope $end
$scope module std_logic_1164 $end
$upscope $end
$scope module numeric_std $end
$upscope $end
$scope module average $end
$var reg 1 ! clk $end
$var reg 1 " reset $end
$var reg 10 # a_in[9:0] $end
$var reg 10 $ b_in[9:0] $end
$var reg 10 % avg_out[9:0] $end
$var reg 10 & s_a_in[9:0] $end
$var reg 10 ' s_b_in[9:0] $end
$var reg 11 ( s_avg_out[10:0] $end
$upscope $end
$enddefinitions $end
#0
0!
0"
b0000000000 #
b0000000000 $
b0000000000 %
b0000000000 &
b0000000000 '
b00000000000 (
#5000000
1!
#10000000
0!
#15000000
1!
#20000000
0!
#25000000
1!
#30000000
0!
#35000000
1!
#40000000
0!
#45000000
1!
#50000000
0!
#55000000
1!
#60000000
0!
#65000000
1!
#70000000
0!
#75000000
1!
#80000000
0!
#85000000
1!
#90000000
0!
#95000000
1!
#100000000
0!
#105000000
1!
#110000000
0!
#115000000
1!
#120000000
0!
#125000000
1!
#130000000
0!
#135000000
1!
#140000000
0!
#145000000
1!
#150000000
0!
#155000000
1!
#160000000
0!
#165000000
1!
#170000000
0!
#175000000
1!
#180000000
0!
#185000000
1!
#190000000
0!
#195000000
1!
#200000000
0!
b0010011100 #
b0011001001 $
#205000000
1!
b0010011100 &
b0011001001 '
#210000000
0!
#215000000
1!
b00101100101 (
#220000000
0!
#225000000
1!
b0010110010 %
#230000000
0!
#235000000
1!
#240000000
0!
#245000000
1!
#250000000
0!
b0111011000 #
b0101011000 $
#255000000
1!
b0111011000 &
b0101011000 '
#260000000
0!
#265000000
1!
b01100110000 (
#270000000
0!
#275000000
1!
b0110011000 %
#280000000
0!
#285000000
1!
#290000000
0!
#295000000
1!
#300000000
0!
b1100000101 #
b1100011010 $
#305000000
1!
b1100000101 &
b1100011010 '
#310000000
0!
#315000000
1!
b11000011111 (
#320000000
0!
#325000000
1!
b1100001111 %
#330000000
0!
#335000000
1!
#340000000
0!
#345000000
1!
#350000000
0!
b0110001000 #
b0010110011 $
#355000000
1!
b0110001000 &
b0010110011 '
#360000000
0!
#365000000
1!
b01000111011 (
#370000000
0!
#375000000
1!
b0100011101 %
#380000000
0!
#385000000
1!
#390000000
0!
#395000000
1!
#400000000
0!
b0111011000 #
b1101110001 $
#405000000
1!
b0111011000 &
b1101110001 '
#410000000
0!
#415000000
1!
b10101001001 (
#420000000
0!
#425000000
1!
b1010100100 %
#430000000
0!
#435000000
1!
#440000000
0!
#445000000
1!
#450000000
0!
b1010111111 #
b0100011100 $
#455000000
1!
b1010111111 &
b0100011100 '
#460000000
0!
#465000000
1!
b01111011011 (
#470000000
0!
#475000000
1!
b0111101101 %
#480000000
0!
#485000000
1!
#490000000
0!
#495000000
1!
#500000000
0!
b0001100001 #
b0101110101 $
#505000000
1!
b0001100001 &
b0101110101 '
#510000000
0!
#515000000
1!
b00111010110 (
#520000000
0!
#525000000
1!
b0011101011 %
#530000000
0!
#535000000
1!
#540000000
0!
#545000000
1!
#550000000
0!
b1010001110 #
b1110010110 $
#555000000
1!
b1010001110 &
b1110010110 '
#560000000
0!
#565000000
1!
b11000100100 (
#570000000
0!
#575000000
1!
b1100010010 %
#580000000
0!
#585000000
1!
#590000000
0!
#595000000
1!
#600000000
0!
b0000111000 #
b0111110111 $
#605000000
1!
b0000111000 &
b0111110111 '
#610000000
0!
#615000000
1!
b01000101111 (
#620000000
0!
#625000000
1!
b0100010111 %
#630000000
0!
#635000000
1!
#640000000
0!
#645000000
1!
#650000000
0!
b1111011101 #
b0010110011 $
#655000000
1!
b1111011101 &
b0010110011 '
#660000000
0!
#665000000
1!
b10010010000 (
#670000000
0!
#675000000
1!
b1001001000 %
#680000000
0!
#685000000
1!
#690000000
0!
#695000000
1!
#700000000
0!
b0110101010 #
b1111011010 $
#705000000
1!
b0110101010 &
b1111011010 '
#710000000
0!
#715000000
1!
b10110000100 (
#720000000
0!
#725000000
1!
b1011000010 %
#730000000
0!
#735000000
1!
#740000000
0!
#745000000
1!
#750000000
0!
b0101001111 #
b0111010000 $
#755000000
1!
b0101001111 &
b0111010000 '
#760000000
0!
#765000000
1!
b01100011111 (
#770000000
0!
#775000000
1!
b0110001111 %
#780000000
0!
#785000000
1!
#790000000
0!
#795000000
1!
#800000000
0!
b0010001010 #
b0010011010 $
#805000000
1!
b0010001010 &
b0010011010 '
#810000000
0!
#815000000
1!
b00100100100 (
#820000000
0!
#825000000
1!
b0010010010 %
#830000000
0!
#835000000
1!
#840000000
0!
#845000000
1!
#850000000
0!
b1011111010 #
b1110110110 $
#855000000
1!
b1011111010 &
b1110110110 '
#860000000
0!
#865000000
1!
b11010110000 (
#870000000
0!
#875000000
1!
b1101011000 %
#880000000
0!
#885000000
1!
#890000000
0!
#895000000
1!
#900000000
0!
b1110000001 #
b1000001010 $
#905000000
1!
b1110000001 &
b1000001010 '
#910000000
0!
#915000000
1!
b10110001011 (
#920000000
0!
#925000000
1!
b1011000101 %
#930000000
0!
#935000000
1!
#940000000
0!
#945000000
1!
#950000000
0!
b0110100000 #
b0101000110 $
#955000000
1!
b0110100000 &
b0101000110 '
#960000000
0!
#965000000
1!
b01011100110 (
#970000000
0!
#975000000
1!
b0101110011 %
#980000000
0!
#985000000
1!
#990000000
0!
#995000000
1!
#1000000000
0!
b0101001001 #
b1010110100 $
#1005000000
1!
b0101001001 &
b1010110100 '
#1010000000
0!
#1015000000
1!
b01111111101 (
#1020000000
0!
#1025000000
1!
b0111111110 %
#1030000000
0!
#1035000000
1!
#1040000000
0!
#1045000000
1!
#1050000000
0!
b1011111100 #
b0101100110 $
#1055000000
1!
b1011111100 &
b0101100110 '
#1060000000
0!
#1065000000
1!
b10001100010 (
#1070000000
0!
#1075000000
1!
b1000110001 %
#1080000000
0!
#1085000000
1!
#1090000000
0!
#1095000000
1!
#1100000000
0!
b1000010010 #
b1101001100 $
#1105000000
1!
b1000010010 &
b1101001100 '
#1110000000
0!
#1115000000
1!
b10101011110 (
#1120000000
0!
#1125000000
1!
b1010101111 %
#1130000000
0!
#1135000000
1!
#1140000000
0!
#1145000000
1!
#1150000000
0!
b0100111001 #
b0011001001 $
#1155000000
1!
b0100111001 &
b0011001001 '
#1160000000
0!
#1165000000
1!
b01000000010 (
#1170000000
0!
#1175000000
1!
b0100000001 %
#1180000000
0!
#1185000000
1!
#1190000000
0!
#1195000000
1!
#1200000000
0!
b0001010101 #
b1101010101 $
#1205000000
1!
b0001010101 &
b1101010101 '
#1210000000
0!
#1215000000
1!
b01110101010 (
#1220000000
0!
#1225000000
1!
b0111010101 %
#1230000000
0!
#1235000000
1!
#1240000000
0!
#1245000000
1!
#1250000000
0!
b0100011000 #
b0000011010 $
#1255000000
1!
b0100011000 &
b0000011010 '
#1260000000
0!
#1265000000
1!
b00100110010 (
#1270000000
0!
#1275000000
1!
b0010011001 %
#1280000000
0!
#1285000000
1!
#1290000000
0!
#1295000000
1!
#1300000000
0!
b1101100110 #
b0001100101 $
#1305000000
1!
b1101100110 &
b0001100101 '
#1310000000
0!
#1315000000
1!
b01111001011 (
#1320000000
0!
#1325000000
1!
b0111100101 %
#1330000000
0!
#1335000000
1!
#1340000000
0!
#1345000000
1!
#1350000000
0!
b1110100101 #
b1110011010 $
#1355000000
1!
b1110100101 &
b1110011010 '
#1360000000
0!
#1365000000
1!
b11100111111 (
#1370000000
0!
#1375000000
1!
b1110011111 %
#1380000000
0!
#1385000000
1!
#1390000000
0!
#1395000000
1!
#1400000000
0!
b1101001011 #
b1111001010 $
#1405000000
1!
b1101001011 &
b1111001010 '
#1410000000
0!
#1415000000
1!
b11100010101 (
#1420000000
0!
#1425000000
1!
b1110001010 %
#1430000000
0!
#1435000000
1!
#1440000000
0!
#1445000000
1!
#1450000000
0!
b0100001010 #
b0010100111 $
#1455000000
1!
b0100001010 &
b0010100111 '
#1460000000
0!
#1465000000
1!
b00110110001 (
#1470000000
0!
#1475000000
1!
b0011011000 %
#1480000000
0!
#1485000000
1!
#1490000000
0!
#1495000000
1!
#1500000000
0!
b1011011100 #
b0001000000 $
#1505000000
1!
b1011011100 &
b0001000000 '
#1510000000
0!
#1515000000
1!
b01100011100 (
#1520000000
0!
#1525000000
1!
b0110001110 %
#1530000000
0!
#1535000000
1!
#1540000000
0!
#1545000000
1!
#1550000000
0!
b1011111000 #
b1010111001 $
#1555000000
1!
b1011111000 &
b1010111001 '
#1560000000
0!
#1565000000
1!
b10110110001 (
#1570000000
0!
#1575000000
1!
b1011011000 %
#1580000000
0!
#1585000000
1!
#1590000000
0!
#1595000000
1!
#1600000000
0!
b1100000101 #
b1100100000 $
#1605000000
1!
b1100000101 &
b1100100000 '
#1610000000
0!
#1615000000
1!
b11000100101 (
#1620000000
0!
#1625000000
1!
b1100010010 %
#1630000000
0!
#1635000000
1!
#1640000000
0!
#1645000000
1!
#1650000000
0!
b0011100010 #
b1100010010 $
#1655000000
1!
b0011100010 &
b1100010010 '
#1660000000
0!
#1665000000
1!
b01111110100 (
#1670000000
0!
#1675000000
1!
b0111111010 %
#1680000000
0!
#1685000000
1!
#1690000000
0!
#1695000000
1!
#1700000000
0!
b0010101100 #
b1101100001 $
#1705000000
1!
b0010101100 &
b1101100001 '
#1710000000
0!
#1715000000
1!
b10000001101 (
#1720000000
0!
#1725000000
1!
b1000000110 %
#1730000000
0!
#1735000000
1!
#1740000000
0!
#1745000000
1!
#1750000000
0!
b1100011100 #
b0110101000 $
#1755000000
1!
b1100011100 &
b0110101000 '
#1760000000
0!
#1765000000
1!
b10011000100 (
#1770000000
0!
#1775000000
1!
b1001100010 %
#1780000000
0!
#1785000000
1!
#1790000000
0!
#1795000000
1!
#1800000000
0!
b1111111101 #
b1010111111 $
#1805000000
1!
b1111111101 &
b1010111111 '
#1810000000
0!
#1815000000
1!
b11010111100 (
#1820000000
0!
#1825000000
1!
b1101011110 %
#1830000000
0!
#1835000000
1!
#1840000000
0!
#1845000000
1!
#1850000000
0!
b1001001000 #
b0010110000 $
#1855000000
1!
b1001001000 &
b0010110000 '
#1860000000
0!
#1865000000
1!
b01011111000 (
#1870000000
0!
#1875000000
1!
b0101111100 %
#1880000000
0!
#1885000000
1!
#1890000000
0!
#1895000000
1!
#1900000000
0!
b1011000101 #
b0101111010 $
#1905000000
1!
b1011000101 &
b0101111010 '
#1910000000
0!
#1915000000
1!
b10000111111 (
#1920000000
0!
#1925000000
1!
b1000011111 %
#1930000000
0!
#1935000000
1!
#1940000000
0!
#1945000000
1!
#1950000000
0!
b1101011001 #
b0110000010 $
#1955000000
1!
b1101011001 &
b0110000010 '
#1960000000
0!
#1965000000
1!
b10011011011 (
#1970000000
0!
#1975000000
1!
b1001101101 %
#1980000000
0!
#1985000000
1!
#1990000000
0!
#1995000000
1!
#2000000000
0!
b0010110111 #
b1111011101 $
#2005000000
1!
b0010110111 &
b1111011101 '
#2010000000
0!
#2015000000
1!
b10010010100 (
#2020000000
0!
#2025000000
1!
b1001001010 %
#2030000000
0!
#2035000000
1!
#2040000000
0!
#2045000000
1!
#2050000000
0!
b1011001011 #
b1101111100 $
#2055000000
1!
b1011001011 &
b1101111100 '
#2060000000
0!
#2065000000
1!
b11001000111 (
#2070000000
0!
#2075000000
1!
b1100100011 %
#2080000000
0!
#2085000000
1!
#2090000000
0!
#2095000000
1!
#2100000000
0!
b1101010001 #
b0010100101 $
#2105000000
1!
b1101010001 &
b0010100101 '
#2110000000
0!
#2115000000
1!
b01111110110 (
#2120000000
0!
#2125000000
1!
b0111111011 %
#2130000000
0!
#2135000000
1!
#2140000000
0!
#2145000000
1!
#2150000000
0!
b1111000010 #
b0111000110 $
#2155000000
1!
b1111000010 &
b0111000110 '
#2160000000
0!
#2165000000
1!
b10110001000 (
#2170000000
0!
#2175000000
1!
b1011000100 %
#2180000000
0!
#2185000000
1!
#2190000000
0!
#2195000000
1!
#2200000000
0!
b0111010001 #
b1000001000 $
#2205000000
1!
b0111010001 &
b1000001000 '
#2210000000
0!
#2215000000
1!
b01111011001 (
#2220000000
0!
#2225000000
1!
b0111101100 %
#2230000000
0!
#2235000000
1!
#2240000000
0!
#2245000000
1!
#2250000000
0!
b0111110000 #
b0101001111 $
#2255000000
1!
b0111110000 &
b0101001111 '
#2260000000
0!
#2265000000
1!
b01100111111 (
#2270000000
0!
#2275000000
1!
b0110011111 %
#2280000000
0!
#2285000000
1!
#2290000000
0!
#2295000000
1!
#2300000000
0!
b0000001000 #
b0100111010 $
#2305000000
1!
b0000001000 &
b0100111010 '
#2310000000
0!
#2315000000
1!
b00101000010 (
#2320000000
0!
#2325000000
1!
b0010100001 %
#2330000000
0!
#2335000000
1!
#2340000000
0!
#2345000000
1!
#2350000000
0!
b0001100010 #
b1001000101 $
#2355000000
1!
b0001100010 &
b1001000101 '
#2360000000
0!
#2365000000
1!
b01010100111 (
#2370000000
0!
#2375000000
1!
b0101010011 %
#2380000000
0!
#2385000000
1!
#2390000000
0!
#2395000000
1!
#2400000000
0!
b0110000001 #
b1010001111 $
#2405000000
1!
b0110000001 &
b1010001111 '
#2410000000
0!
#2415000000
1!
b10000010000 (
#2420000000
0!
#2425000000
1!
b1000001000 %
#2430000000
0!
#2435000000
1!
#2440000000
0!
#2445000000
1!
#2450000000
0!
b0111110001 #
b0000100100 $
#2455000000
1!
b0111110001 &
b0000100100 '
#2460000000
0!
#2465000000
1!
b01000010101 (
#2470000000
0!
#2475000000
1!
b0100001010 %
#2480000000
0!
#2485000000
1!
#2490000000
0!
#2495000000
1!
#2500000000
0!
b1011110010 #
b0101101011 $
#2505000000
1!
b1011110010 &
b0101101011 '
#2510000000
0!
#2515000000
1!
b10001011101 (
#2520000000
0!
#2525000000
1!
b1000101110 %
#2530000000
0!
#2535000000
1!
#2540000000
0!
#2545000000
1!
#2550000000
0!
b1101011101 #
b1011100110 $
#2555000000
1!
b1101011101 &
b1011100110 '
#2560000000
0!
#2565000000
1!
b11001000011 (
#2570000000
0!
#2575000000
1!
b1100100001 %
#2580000000
0!
#2585000000
1!
#2590000000
0!
#2595000000
1!
#2600000000
0!
b0011011100 #
b0000001010 $
#2605000000
1!
b0011011100 &
b0000001010 '
#2610000000
0!
#2615000000
1!
b00011100110 (
#2620000000
0!
#2625000000
1!
b0001110011 %
#2630000000
0!
#2635000000
1!
#2640000000
0!
#2645000000
1!
#2650000000
0!
b1010111110 #
b1011111000 $
#2655000000
1!
b1010111110 &
b1011111000 '
#2660000000
0!
#2665000000
1!
b10110110110 (
#2670000000
0!
#2675000000
1!
b1011011011 %
#2680000000
0!
#2685000000
1!
#2690000000
0!
#2695000000
1!
#2700000000
0!
b1001010011 #
b1010011110 $
#2705000000
1!
b1001010011 &
b1010011110 '
#2710000000
0!
#2715000000
1!
b10011110001 (
#2720000000
0!
#2725000000
1!
b1001111000 %
#2730000000
0!
#2735000000
1!
#2740000000
0!
#2745000000
1!
#2750000000
0!
b1010000110 #
b1111101010 $
#2755000000
1!
b1010000110 &
b1111101010 '
#2760000000
0!
#2765000000
1!
b11001110000 (
#2770000000
0!
#2775000000
1!
b1100111000 %
#2780000000
0!
#2785000000
1!
#2790000000
0!
#2795000000
1!
#2800000000
0!
b1100011111 #
b1001011001 $
#2805000000
1!
b1100011111 &
b1001011001 '
#2810000000
0!
#2815000000
1!
b10101111000 (
#2820000000
0!
#2825000000
1!
b1010111100 %
#2830000000
0!
#2835000000
1!
#2840000000
0!
#2845000000
1!
#2850000000
0!
b1001110101 #
b0001101101 $
#2855000000
1!
b1001110101 &
b0001101101 '
#2860000000
0!
#2865000000
1!
b01011100010 (
#2870000000
0!
#2875000000
1!
b0101110001 %
#2880000000
0!
#2885000000
1!
#2890000000
0!
#2895000000
1!
#2900000000
0!
b0110111101 #
b0100011110 $
#2905000000
1!
b0110111101 &
b0100011110 '
#2910000000
0!
#2915000000
1!
b01011011011 (
#2920000000
0!
#2925000000
1!
b0101101101 %
#2930000000
0!
#2935000000
1!
#2940000000
0!
#2945000000
1!
#2950000000
0!
b1001100011 #
b1011011100 $
#2955000000
1!
b1001100011 &
b1011011100 '
#2960000000
0!
#2965000000
1!
b10100111111 (
#2970000000
0!
#2975000000
1!
b1010011111 %
#2980000000
0!
#2985000000
1!
#2990000000
0!
#2995000000
1!
#3000000000
0!
b0010110111 #
b0011011010 $
#3005000000
1!
b0010110111 &
b0011011010 '
#3010000000
0!
#3015000000
1!
b00110010001 (
#3020000000
0!
#3025000000
1!
b0011001000 %
#3030000000
0!
#3035000000
1!
#3040000000
0!
#3045000000
1!
#3050000000
0!
b1100010001 #
b1100000101 $
#3055000000
1!
b1100010001 &
b1100000101 '
#3060000000
0!
#3065000000
1!
b11000010110 (
#3070000000
0!
#3075000000
1!
b1100001011 %
#3080000000
0!
#3085000000
1!
#3090000000
0!
#3095000000
1!
#3100000000
0!
b1010101111 #
b1011001110 $
#3105000000
1!
b1010101111 &
b1011001110 '
#3110000000
0!
#3115000000
1!
b10101111101 (
#3120000000
0!
#3125000000
1!
b1010111110 %
#3130000000
0!
#3135000000
1!
#3140000000
0!
#3145000000
1!
#3150000000
0!
b1010110011 #
b1111000100 $
#3155000000
1!
b1010110011 &
b1111000100 '
#3160000000
0!
#3165000000
1!
b11001110111 (
#3170000000
0!
#3175000000
1!
b1100111011 %
#3180000000
0!
#3185000000
1!
#3190000000
0!
#3195000000
1!
#3200000000
0!
b1001101101 #
b0111101000 $
#3205000000
1!
b1001101101 &
b0111101000 '
#3210000000
0!
#3215000000
1!
b10001010101 (
#3220000000
0!
#3225000000
1!
b1000101010 %
#3230000000
0!
#3235000000
1!
#3240000000
0!
#3245000000
1!
#3250000000
0!
b1000100100 #
b1101101110 $
#3255000000
1!
b1000100100 &
b1101101110 '
#3260000000
0!
#3265000000
1!
b10110010010 (
#3270000000
0!
#3275000000
1!
b1011001001 %
#3280000000
0!
#3285000000
1!
#3290000000
0!
#3295000000
1!
#3300000000
0!
b1101000001 #
b1101000011 $
#3305000000
1!
b1101000001 &
b1101000011 '
#3310000000
0!
#3315000000
1!
b11010000100 (
#3320000000
0!
#3325000000
1!
b1101000010 %
#3330000000
0!
#3335000000
1!
#3340000000
0!
#3345000000
1!
#3350000000
0!
b1010100010 #
b1011001110 $
#3355000000
1!
b1010100010 &
b1011001110 '
#3360000000
0!
#3365000000
1!
b10101110000 (
#3370000000
0!
#3375000000
1!
b1010111000 %
#3380000000
0!
#3385000000
1!
#3390000000
0!
#3395000000
1!
#3400000000
0!
b0001111001 #
b0101101100 $
#3405000000
1!
b0001111001 &
b0101101100 '
#3410000000
0!
#3415000000
1!
b00111100101 (
#3420000000
0!
#3425000000
1!
b0011110010 %
#3430000000
0!
#3435000000
1!
#3440000000
0!
#3445000000
1!
#3450000000
0!
b1111011101 #
b1010111000 $
#3455000000
1!
b1111011101 &
b1010111000 '
#3460000000
0!
#3465000000
1!
b11010010101 (
#3470000000
0!
#3475000000
1!
b1101001010 %
#3480000000
0!
#3485000000
1!
#3490000000
0!
#3495000000
1!
#3500000000
0!
b1000110001 #
b1001100011 $
#3505000000
1!
b1000110001 &
b1001100011 '
#3510000000
0!
#3515000000
1!
b10010010100 (
#3520000000
0!
#3525000000
1!
b1001001010 %
#3530000000
0!
#3535000000
1!
#3540000000
0!
#3545000000
1!
#3550000000
0!
b0010011111 #
b0001111000 $
#3555000000
1!
b0010011111 &
b0001111000 '
#3560000000
0!
#3565000000
1!
b00100010111 (
#3570000000
0!
#3575000000
1!
b0010001011 %
#3580000000
0!
#3585000000
1!
#3590000000
0!
#3595000000
1!
#3600000000
0!
b0001011010 #
b0100011101 $
#3605000000
1!
b0001011010 &
b0100011101 '
#3610000000
0!
#3615000000
1!
b00101110111 (
#3620000000
0!
#3625000000
1!
b0010111011 %
#3630000000
0!
#3635000000
1!
#3640000000
0!
#3645000000
1!
#3650000000
0!
b0001101011 #
b0111101011 $
#3655000000
1!
b0001101011 &
b0111101011 '
#3660000000
0!
#3665000000
1!
b01001010110 (
#3670000000
0!
#3675000000
1!
b0100101011 %
#3680000000
0!
#3685000000
1!
#3690000000
0!
#3695000000
1!
#3700000000
0!
b0110010011 #
b0111001111 $
#3705000000
1!
b0110010011 &
b0111001111 '
#3710000000
0!
#3715000000
1!
b01101100010 (
#3720000000
0!
#3725000000
1!
b0110110001 %
#3730000000
0!
#3735000000
1!
#3740000000
0!
#3745000000
1!
#3750000000
0!
b0010001100 #
b1101010001 $
#3755000000
1!
b0010001100 &
b1101010001 '
#3760000000
0!
#3765000000
1!
b01111011101 (
#3770000000
0!
#3775000000
1!
b0111101110 %
#3780000000
0!
#3785000000
1!
#3790000000
0!
#3795000000
1!
#3800000000
0!
b1100010011 #
b1011100100 $
#3805000000
1!
b1100010011 &
b1011100100 '
#3810000000
0!
#3815000000
1!
b10111110111 (
#3820000000
0!
#3825000000
1!
b1011111011 %
#3830000000
0!
#3835000000
1!
#3840000000
0!
#3845000000
1!
#3850000000
0!
b1100101101 #
b1101110100 $
#3855000000
1!
b1100101101 &
b1101110100 '
#3860000000
0!
#3865000000
1!
b11010100001 (
#3870000000
0!
#3875000000
1!
b1101010000 %
#3880000000
0!
#3885000000
1!
#3890000000
0!
#3895000000
1!
#3900000000
0!
b1110101111 #
b1101011101 $
#3905000000
1!
b1110101111 &
b1101011101 '
#3910000000
0!
#3915000000
1!
b11100001100 (
#3920000000
0!
#3925000000
1!
b1110000110 %
#3930000000
0!
#3935000000
1!
#3940000000
0!
#3945000000
1!
#3950000000
0!
b1101010000 #
b1000010000 $
#3955000000
1!
b1101010000 &
b1000010000 '
#3960000000
0!
#3965000000
1!
b10101100000 (
#3970000000
0!
#3975000000
1!
b1010110000 %
#3980000000
0!
#3985000000
1!
#3990000000
0!
#3995000000
1!
#4000000000
0!
b1000010110 #
b0101111111 $
#4005000000
1!
b1000010110 &
b0101111111 '
#4010000000
0!
#4015000000
1!
b01110010101 (
#4020000000
0!
#4025000000
1!
b0111001010 %
#4030000000
0!
#4035000000
1!
#4040000000
0!
#4045000000
1!
#4050000000
0!
b1010011000 #
b1110010000 $
#4055000000
1!
b1010011000 &
b1110010000 '
#4060000000
0!
#4065000000
1!
b11000101000 (
#4070000000
0!
#4075000000
1!
b1100010100 %
#4080000000
0!
#4085000000
1!
#4090000000
0!
#4095000000
1!
#4100000000
0!
b0010000101 #
b1001111101 $
#4105000000
1!
b0010000101 &
b1001111101 '
#4110000000
0!
#4115000000
1!
b01100000010 (
#4120000000
0!
#4125000000
1!
b0110000001 %
#4130000000
0!
#4135000000
1!
#4140000000
0!
#4145000000
1!
#4150000000
0!
b0001011110 #
b0001100001 $
#4155000000
1!
b0001011110 &
b0001100001 '
#4160000000
0!
#4165000000
1!
b00010111111 (
#4170000000
0!
#4175000000
1!
b0001011111 %
#4180000000
0!
#4185000000
1!
#4190000000
0!
#4195000000
1!
#4200000000
0!
b1010011001 #
b0111110000 $
#4205000000
1!
b1010011001 &
b0111110000 '
#4210000000
0!
#4215000000
1!
b10010001001 (
#4220000000
0!
#4225000000
1!
b1001000100 %
#4230000000
0!
#4235000000
1!
#4240000000
0!
#4245000000
1!
#4250000000
0!
b0001011100 #
b1000100000 $
#4255000000
1!
b0001011100 &
b1000100000 '
#4260000000
0!
#4265000000
1!
b01001111100 (
#4270000000
0!
#4275000000
1!
b0100111110 %
#4280000000
0!
#4285000000
1!
#4290000000
0!
#4295000000
1!
#4300000000
0!
b1000011011 #
b0110111000 $
#4305000000
1!
b1000011011 &
b0110111000 '
#4310000000
0!
#4315000000
1!
b01111010011 (
#4320000000
0!
#4325000000
1!
b0111101001 %
#4330000000
0!
#4335000000
1!
#4340000000
0!
#4345000000
1!
#4350000000
0!
b1110011001 #
b0111010100 $
#4355000000
1!
b1110011001 &
b0111010100 '
#4360000000
0!
#4365000000
1!
b10101101101 (
#4370000000
0!
#4375000000
1!
b1010110110 %
#4380000000
0!
#4385000000
1!
#4390000000
0!
#4395000000
1!
#4400000000
0!
b0100101100 #
b0111101100 $
#4405000000
1!
b0100101100 &
b0111101100 '
#4410000000
0!
#4415000000
1!
b01100011000 (
#4420000000
0!
#4425000000
1!
b0110001100 %
#4430000000
0!
#4435000000
1!
#4440000000
0!
#4445000000
1!
#4450000000
0!
b0011110000 #
b1010101110 $
#4455000000
1!
b0011110000 &
b1010101110 '
#4460000000
0!
#4465000000
1!
b01110011110 (
#4470000000
0!
#4475000000
1!
b0111001111 %
#4480000000
0!
#4485000000
1!
#4490000000
0!
#4495000000
1!
#4500000000
0!
b1001111000 #
b1010001100 $
#4505000000
1!
b1001111000 &
b1010001100 '
#4510000000
0!
#4515000000
1!
b10100000100 (
#4520000000
0!
#4525000000
1!
b1010000010 %
#4530000000
0!
#4535000000
1!
#4540000000
0!
#4545000000
1!
#4550000000
0!
b1010111001 #
b0001001110 $
#4555000000
1!
b1010111001 &
b0001001110 '
#4560000000
0!
#4565000000
1!
b01100000111 (
#4570000000
0!
#4575000000
1!
b0110000011 %
#4580000000
0!
#4585000000
1!
#4590000000
0!
#4595000000
1!
#4600000000
0!
b1011110111 #
b1100111100 $
#4605000000
1!
b1011110111 &
b1100111100 '
#4610000000
0!
#4615000000
1!
b11000110011 (
#4620000000
0!
#4625000000
1!
b1100011001 %
#4630000000
0!
#4635000000
1!
#4640000000
0!
#4645000000
1!
#4650000000
0!
b1000111110 #
b0010000110 $
#4655000000
1!
b1000111110 &
b0010000110 '
#4660000000
0!
#4665000000
1!
b01011000100 (
#4670000000
0!
#4675000000
1!
b0101100010 %
#4680000000
0!
#4685000000
1!
#4690000000
0!
#4695000000
1!
#4700000000
0!
b1010010000 #
b0100001101 $
#4705000000
1!
b1010010000 &
b0100001101 '
#4710000000
0!
#4715000000
1!
b01110011101 (
#4720000000
0!
#4725000000
1!
b0111001110 %
#4730000000
0!
#4735000000
1!
#4740000000
0!
#4745000000
1!
#4750000000
0!
b1000100010 #
b1001111101 $
#4755000000
1!
b1000100010 &
b1001111101 '
#4760000000
0!
#4765000000
1!
b10010011111 (
#4770000000
0!
#4775000000
1!
b1001001111 %
#4780000000
0!
#4785000000
1!
#4790000000
0!
#4795000000
1!
#4800000000
0!
b0001100111 #
b0110101101 $
#4805000000
1!
b0001100111 &
b0110101101 '
#4810000000
0!
#4815000000
1!
b01000010100 (
#4820000000
0!
#4825000000
1!
b0100001010 %
#4830000000
0!
#4835000000
1!
#4840000000
0!
#4845000000
1!
#4850000000
0!
b0110010001 #
b1101110011 $
#4855000000
1!
b0110010001 &
b1101110011 '
#4860000000
0!
#4865000000
1!
b10100000100 (
#4870000000
0!
#4875000000
1!
b1010000010 %
#4880000000
0!
#4885000000
1!
#4890000000
0!
#4895000000
1!
#4900000000
0!
b1111111101 #
b0001100001 $
#4905000000
1!
b1111111101 &
b0001100001 '
#4910000000
0!
#4915000000
1!
b10001011110 (
#4920000000
0!
#4925000000
1!
b1000101111 %
#4930000000
0!
#4935000000
1!
#4940000000
0!
#4945000000
1!
#4950000000
0!
b0011001111 #
b0100010010 $
#4955000000
1!
b0011001111 &
b0100010010 '
#4960000000
0!
#4965000000
1!
b00111100001 (
#4970000000
0!
#4975000000
1!
b0011110000 %
#4980000000
0!
#4985000000
1!
#4990000000
0!
#4995000000
1!
#5000000000
0!
b0010001111 #
b1100010001 $
#5005000000
1!
b0010001111 &
b1100010001 '
#5010000000
0!
#5015000000
1!
b01110100000 (
#5020000000
0!
#5025000000
1!
b0111010000 %
#5030000000
0!
#5035000000
1!
#5040000000
0!
#5045000000
1!
#5050000000
0!
b1010000011 #
b1100100001 $
#5055000000
1!
b1010000011 &
b1100100001 '
#5060000000
0!
#5065000000
1!
b10110100100 (
#5070000000
0!
#5075000000
1!
b1011010010 %
#5080000000
0!
#5085000000
1!
#5090000000
0!
#5095000000
1!
#5100000000
0!
b0110011001 #
b1001000010 $
#5105000000
1!
b0110011001 &
b1001000010 '
#5110000000
0!
#5115000000
1!
b01111011011 (
#5120000000
0!
#5125000000
1!
b0111101101 %
#5130000000
0!
#5135000000
1!
#5140000000
0!
#5145000000
1!
#5150000000
0!
b1011001100 #
b0001010101 $
#5155000000
1!
b1011001100 &
b0001010101 '
#5160000000
0!
#5165000000
1!
b01100100001 (
#5170000000
0!
#5175000000
1!
b0110010000 %
#5180000000
0!
#5185000000
1!
#5190000000
0!
#5195000000
1!
#5200000000
0!
b1011100001 #
b1011010001 $
#5205000000
1!
b1011100001 &
b1011010001 '
#5210000000
0!
#5215000000
1!
b10110110010 (
#5220000000
0!
#5225000000
1!
b1011011001 %
#5230000000
0!
#5235000000
1!
#5240000000
0!
#5245000000
1!
